UseJenkins.py
UseJenkins-0.0.4.dist-info/METADATA
UseJenkins-0.0.4.dist-info/RECORD
UseJenkins-0.0.4.dist-info/WHEEL
UseJenkins-0.0.4.dist-info/top_level.txt
