Metadata-Version: 2.1
Name: UseJenkins
Version: 0.0.4
Summary: How to Use Jenkins！
Home-page: https://github.com/fangbinbin30
Author: Fangbinbin
Author-email: fangbinbin30@163.com
License: UNKNOWN
Keywords: jenkins
Platform: UNKNOWN
Classifier: Programming Language :: Python :: 3
Classifier: License :: OSI Approved :: MIT License
Classifier: Operating System :: OS Independent
Requires-Dist: jenkins
